{
  "entityType" : "NOTIFICATION_RULE",
  "entity" : {
    "additionalConfig" : {
      "description" : "Send notification to tenant admins when an alarm is created"
    },
    "enabled" : true,
    "externalId" : null,
    "id" : {
      "entityType" : "NOTIFICATION_RULE",
      "id" : "9f1eebd0-cd22-11ee-b180-19b6c811311f"
    },
    "name" : "New alarm",
    "recipientsConfig" : {
      "escalationTable" : {
        "0" : [ "9f135310-cd22-11ee-b180-19b6c811311f" ]
      },
      "triggerType" : "ALARM"
    },
    "templateId" : {
      "entityType" : "NOTIFICATION_TEMPLATE",
      "id" : "9f1b6960-cd22-11ee-b180-19b6c811311f"
    },
    "triggerConfig" : {
      "triggerType" : "ALARM",
      "alarmSeverities" : null,
      "alarmTypes" : null,
      "clearRule" : null,
      "notifyOn" : [ "CREATED" ],
      "triggerType" : "ALARM"
    },
    "triggerType" : "ALARM"
  },
  "relations" : [ ],
  "attributes" : {
    "SERVER_SCOPE" : [ ]
  }
}