{
  "entityType" : "NOTIFICATION_RULE",
  "entity" : {
    "additionalConfig" : {
      "description" : "Send notification to user when any alarm was assigned to him"
    },
    "enabled" : true,
    "externalId" : null,
    "id" : {
      "entityType" : "NOTIFICATION_RULE",
      "id" : "9f361d50-cd22-11ee-b180-19b6c811311f"
    },
    "name" : "Alarm assignment",
    "recipientsConfig" : {
      "targets" : [ "9f19e2c0-cd22-11ee-b180-19b6c811311f" ],
      "triggerType" : "ALARM_ASSIGNMENT"
    },
    "templateId" : {
      "entityType" : "NOTIFICATION_TEMPLATE",
      "id" : "9f3532f0-cd22-11ee-b180-19b6c811311f"
    },
    "triggerConfig" : {
      "triggerType" : "ALARM_ASSIGNMENT",
      "alarmSeverities" : null,
      "alarmStatuses" : null,
      "alarmTypes" : null,
      "notifyOn" : [ "ASSIGNED" ],
      "triggerType" : "ALARM_ASSIGNMENT"
    },
    "triggerType" : "ALARM_ASSIGNMENT"
  },
  "relations" : [ ],
  "attributes" : {
    "SERVER_SCOPE" : [ ]
  }
}